{"nearTen":{"type":"BatWorld","batTests":[{"test":"nearTen(12)=null","answered":false,"correct":false,"visible":true},{"test":"nearTen(17)=null","answered":false,"correct":false,"visible":true},{"test":"nearTen(19)=null","answered":false,"correct":false,"visible":true},{"test":"nearTen(21)=null","answered":false,"correct":false,"visible":false},{"test":"nearTen(6)=null","answered":false,"correct":false,"visible":false},{"test":"nearTen(10)=null","answered":false,"correct":false,"visible":false},{"test":"nearTen(11)=null","answered":false,"correct":false,"visible":false},{"test":"nearTen(12)=null","answered":false,"correct":false,"visible":false},{"test":"nearTen(13)=null","answered":false,"correct":false,"visible":false},{"test":"nearTen(54)=null","answered":false,"correct":false,"visible":false},{"test":"nearTen(155)=null","answered":false,"correct":false,"visible":false},{"test":"nearTen(158)=null","answered":false,"correct":false,"visible":false},{"test":"nearTen(3)=null","answered":false,"correct":false,"visible":false},{"test":"nearTen(1)=null","answered":false,"correct":false,"visible":false}]}}